[
    {
        "repo_name": "gravitee-io_graviteeio-access-management",
        "commit": "3b353da5a24425e4e40d325433c00f49bbf87ab9",
        "rev_path": "gravitee-am-management-api/gravitee-am-management-api-handlers/gravitee-am-management-api-handlers-oauth2/src/main/java/io/gravitee/am/management/handlers/oauth2/WebMvcConfiguration.java",
        "definition": "@Configuration\n@ComponentScan(\"io.gravitee.am.management.handlers.oauth2.controller\")\n@EnableWebMvc\n@Import(ThymeleafConfiguration.class)\npublic class WebMvcConfiguration extends WebMvcConfigurerAdapter {\n\n    @Autowired\n    private Domain domain;\n\n    @Bean\n    public ScopeApprovalEndpoint accessConfirmationController(ClientDetailsService clientDetailsService,\n                                                              ApprovalStore approvalStore,\n                                                              DomainScopeService scopeService) {\n        ScopeApprovalEndpoint accessConfirmationController = new ScopeApprovalEndpoint();\n        accessConfirmationController.setClientDetailsService(clientDetailsService);\n        accessConfirmationController.setApprovalStore(approvalStore);\n        accessConfirmationController.setScopeService(scopeService);\n        return accessConfirmationController;\n    }\n\n    @Override\n    public void addResourceHandlers(ResourceHandlerRegistry registry) {\n        LoginForm loginForm = domain.getLoginForm();\n        if (loginForm != null && loginForm.isEnabled() && loginForm.getAssets() != null) {\n            registry\n                    .addResourceHandler(\"/oauth/assets/**\", \"/assets/**\")\n                    .addResourceLocations(\"file:\" + loginForm.getAssets());\n        } else {\n            registry\n                    .addResourceHandler(\"/oauth/assets/**\", \"/assets/**\")\n                    .addResourceLocations(\"classpath:/assets/\");\n        }\n    }\n\n    @Override\n    public void configureContentNegotiation(ContentNegotiationConfigurer configurer) {\n        configurer.defaultContentType(MediaType.APPLICATION_JSON);\n    }\n}",
        "package": "package io.gravitee.am.management.handlers.oauth2;",
        "tree_path": "WebMvcConfiguration",
        "name": "WebMvcConfiguration",
        "modifiers": "@Configuration\n@ComponentScan(\"io.gravitee.am.management.handlers.oauth2.controller\")\n@EnableWebMvc\n@Import(ThymeleafConfiguration.class)\npublic",
        "superclass": "extends WebMvcConfigurerAdapter",
        "super_interfaces": null,
        "body": "{\n\n    @Autowired\n    private Domain domain;\n\n    @Bean\n    public ScopeApprovalEndpoint accessConfirmationController(ClientDetailsService clientDetailsService,\n                                                              ApprovalStore approvalStore,\n                                                              DomainScopeService scopeService) {\n        ScopeApprovalEndpoint accessConfirmationController = new ScopeApprovalEndpoint();\n        accessConfirmationController.setClientDetailsService(clientDetailsService);\n        accessConfirmationController.setApprovalStore(approvalStore);\n        accessConfirmationController.setScopeService(scopeService);\n        return accessConfirmationController;\n    }\n\n    @Override\n    public void addResourceHandlers(ResourceHandlerRegistry registry) {\n        LoginForm loginForm = domain.getLoginForm();\n        if (loginForm != null && loginForm.isEnabled() && loginForm.getAssets() != null) {\n            registry\n                    .addResourceHandler(\"/oauth/assets/**\", \"/assets/**\")\n                    .addResourceLocations(\"file:\" + loginForm.getAssets());\n        } else {\n            registry\n                    .addResourceHandler(\"/oauth/assets/**\", \"/assets/**\")\n                    .addResourceLocations(\"classpath:/assets/\");\n        }\n    }\n\n    @Override\n    public void configureContentNegotiation(ContentNegotiationConfigurer configurer) {\n        configurer.defaultContentType(MediaType.APPLICATION_JSON);\n    }\n}",
        "start_point": {
            "row": 39,
            "column": 0
        },
        "end_point": {
            "row": 77,
            "column": 1
        },
        "file_mode": "Renamed-Modified",
        "map_path": "gravitee-am-management-api/gravitee-am-management-api-handlers/gravitee-am-management-api-handlers-admin/src/main/java/io/gravitee/am/management/handlers/admin/WebMvcConfiguration.java",
        "methods": [
            {
                "definition": "@Bean\npublic ScopeApprovalEndpoint accessConfirmationController(ClientDetailsService clientDetailsService,\n                                                          ApprovalStore approvalStore,\n                                                          DomainScopeService scopeService) {\n    ScopeApprovalEndpoint accessConfirmationController = new ScopeApprovalEndpoint();\n    accessConfirmationController.setClientDetailsService(clientDetailsService);\n    accessConfirmationController.setApprovalStore(approvalStore);\n    accessConfirmationController.setScopeService(scopeService);\n    return accessConfirmationController;\n}",
                "name": "accessConfirmationController",
                "modifiers": "@Bean\n    public",
                "return_type": "ScopeApprovalEndpoint",
                "parameters": [
                    {
                        "type": "ClientDetailsService",
                        "name": "clientDetailsService"
                    },
                    {
                        "type": "ApprovalStore",
                        "name": "approvalStore"
                    },
                    {
                        "type": "DomainScopeService",
                        "name": "scopeService"
                    }
                ],
                "body": "{\n    ScopeApprovalEndpoint accessConfirmationController = new ScopeApprovalEndpoint();\n    accessConfirmationController.setClientDetailsService(clientDetailsService);\n    accessConfirmationController.setApprovalStore(approvalStore);\n    accessConfirmationController.setScopeService(scopeService);\n    return accessConfirmationController;\n}",
                "start_point": {
                    "row": 48,
                    "column": 4
                },
                "end_point": {
                    "row": 57,
                    "column": 5
                },
                "method_mode": "Deleted"
            },
            {
                "definition": "@Override\npublic void addResourceHandlers(ResourceHandlerRegistry registry) {\n    LoginForm loginForm = domain.getLoginForm();\n    if (loginForm != null && loginForm.isEnabled() && loginForm.getAssets() != null) {\n        registry\n                .addResourceHandler(\"/oauth/assets/**\", \"/assets/**\")\n                .addResourceLocations(\"file:\" + loginForm.getAssets());\n    } else {\n        registry\n                .addResourceHandler(\"/oauth/assets/**\", \"/assets/**\")\n                .addResourceLocations(\"classpath:/assets/\");\n    }\n}",
                "name": "addResourceHandlers",
                "modifiers": "@Override\n    public",
                "return_type": null,
                "parameters": [
                    {
                        "type": "ResourceHandlerRegistry",
                        "name": "registry"
                    }
                ],
                "body": "{\n    LoginForm loginForm = domain.getLoginForm();\n    if (loginForm != null && loginForm.isEnabled() && loginForm.getAssets() != null) {\n        registry\n                .addResourceHandler(\"/oauth/assets/**\", \"/assets/**\")\n                .addResourceLocations(\"file:\" + loginForm.getAssets());\n    } else {\n        registry\n                .addResourceHandler(\"/oauth/assets/**\", \"/assets/**\")\n                .addResourceLocations(\"classpath:/assets/\");\n    }\n}",
                "start_point": {
                    "row": 59,
                    "column": 4
                },
                "end_point": {
                    "row": 71,
                    "column": 5
                },
                "method_mode": "Unchanged"
            },
            {
                "definition": "@Override\npublic void configureContentNegotiation(ContentNegotiationConfigurer configurer) {\n    configurer.defaultContentType(MediaType.APPLICATION_JSON);\n}",
                "name": "configureContentNegotiation",
                "modifiers": "@Override\n    public",
                "return_type": null,
                "parameters": [
                    {
                        "type": "ContentNegotiationConfigurer",
                        "name": "configurer"
                    }
                ],
                "body": "{\n    configurer.defaultContentType(MediaType.APPLICATION_JSON);\n}",
                "start_point": {
                    "row": 73,
                    "column": 4
                },
                "end_point": {
                    "row": 76,
                    "column": 5
                },
                "method_mode": "Unchanged"
            }
        ],
        "class_mode": "Modified"
    }
]