[
    {
        "rev_path": "org.eclipse.sisu.inject/src/org/eclipse/sisu/space/QualifierCache.java",
        "definition": "final class QualifierCache\n    extends EmptyClassVisitor\n{\n    // ----------------------------------------------------------------------\n    // Constants\n    // ----------------------------------------------------------------------\n\n    private static final String QUALIFIER_DESC = Type.getDescriptor( Qualifier.class );\n\n    // ----------------------------------------------------------------------\n    // Implementation fields\n    // ----------------------------------------------------------------------\n\n    private static final Map<String, Boolean> cachedResults = new ConcurrentHashMap<String, Boolean>( 32, 0.75f, 1 );\n\n    private boolean isQualified;\n\n    // ----------------------------------------------------------------------\n    // Public methods\n    // ----------------------------------------------------------------------\n\n    @Override\n    public AnnotationVisitor visitAnnotation( final String desc, final boolean visible )\n    {\n        isQualified |= QUALIFIER_DESC.equals( desc );\n        return null;\n    }\n\n    // ----------------------------------------------------------------------\n    // Local methods\n    // ----------------------------------------------------------------------\n\n    /**\n     * Attempts to load the potential {@link Qualifier} annotation and return its class.\n     * \n     * @param space The class space\n     * @param desc The annotation descriptor\n     * @return {@code true} if the annotation is a qualifier; otherwise {@code false}\n     */\n    boolean qualify( final ClassSpace space, final String desc )\n    {\n        final Boolean result = cachedResults.get( desc );\n        if ( null == result )\n        {\n            isQualified = false;\n\n            final String name = desc.substring( 1, desc.length() - 1 );\n            ClassSpaceScanner.accept( this, space.getResource( name + \".class\" ) );\n            cachedResults.put( desc, Boolean.valueOf( isQualified ) );\n\n            return isQualified;\n        }\n        return result.booleanValue();\n    }\n}",
        "package": "package org.eclipse.sisu.space;",
        "tree_path": "QualifierCache",
        "name": "QualifierCache",
        "modifiers": "final",
        "superclass": "extends EmptyClassVisitor",
        "super_interfaces": null,
        "body": "{\n    // ----------------------------------------------------------------------\n    // Constants\n    // ----------------------------------------------------------------------\n\n    private static final String QUALIFIER_DESC = Type.getDescriptor( Qualifier.class );\n\n    // ----------------------------------------------------------------------\n    // Implementation fields\n    // ----------------------------------------------------------------------\n\n    private static final Map<String, Boolean> cachedResults = new ConcurrentHashMap<String, Boolean>( 32, 0.75f, 1 );\n\n    private boolean isQualified;\n\n    // ----------------------------------------------------------------------\n    // Public methods\n    // ----------------------------------------------------------------------\n\n    @Override\n    public AnnotationVisitor visitAnnotation( final String desc, final boolean visible )\n    {\n        isQualified |= QUALIFIER_DESC.equals( desc );\n        return null;\n    }\n\n    // ----------------------------------------------------------------------\n    // Local methods\n    // ----------------------------------------------------------------------\n\n    /**\n     * Attempts to load the potential {@link Qualifier} annotation and return its class.\n     * \n     * @param space The class space\n     * @param desc The annotation descriptor\n     * @return {@code true} if the annotation is a qualifier; otherwise {@code false}\n     */\n    boolean qualify( final ClassSpace space, final String desc )\n    {\n        final Boolean result = cachedResults.get( desc );\n        if ( null == result )\n        {\n            isQualified = false;\n\n            final String name = desc.substring( 1, desc.length() - 1 );\n            ClassSpaceScanner.accept( this, space.getResource( name + \".class\" ) );\n            cachedResults.put( desc, Boolean.valueOf( isQualified ) );\n\n            return isQualified;\n        }\n        return result.booleanValue();\n    }\n}",
        "start_point": {
            "row": 24,
            "column": 0
        },
        "end_point": {
            "row": 78,
            "column": 1
        },
        "file_mode": "Modified",
        "map_path": null,
        "methods": [
            {
                "definition": "@Override\npublic AnnotationVisitor visitAnnotation( final String desc, final boolean visible )\n{\n    isQualified |= QUALIFIER_DESC.equals( desc );\n    return null;\n}",
                "name": "visitAnnotation",
                "modifiers": "@Override\n    public",
                "return_type": "AnnotationVisitor",
                "parameters": [
                    {
                        "type": "final",
                        "name": "String"
                    },
                    {
                        "type": "final",
                        "name": "boolean"
                    }
                ],
                "body": "{\n    isQualified |= QUALIFIER_DESC.equals( desc );\n    return null;\n}",
                "start_point": {
                    "row": 45,
                    "column": 4
                },
                "end_point": {
                    "row": 50,
                    "column": 5
                }
            },
            {
                "definition": "boolean qualify( final ClassSpace space, final String desc )\n{\n    final Boolean result = cachedResults.get( desc );\n    if ( null == result )\n    {\n        isQualified = false;\n\n        final String name = desc.substring( 1, desc.length() - 1 );\n        ClassSpaceScanner.accept( this, space.getResource( name + \".class\" ) );\n        cachedResults.put( desc, Boolean.valueOf( isQualified ) );\n\n        return isQualified;\n    }\n    return result.booleanValue();\n}",
                "name": "qualify",
                "modifiers": null,
                "return_type": null,
                "parameters": [
                    {
                        "type": "final",
                        "name": "ClassSpace"
                    },
                    {
                        "type": "final",
                        "name": "String"
                    }
                ],
                "body": "{\n    final Boolean result = cachedResults.get( desc );\n    if ( null == result )\n    {\n        isQualified = false;\n\n        final String name = desc.substring( 1, desc.length() - 1 );\n        ClassSpaceScanner.accept( this, space.getResource( name + \".class\" ) );\n        cachedResults.put( desc, Boolean.valueOf( isQualified ) );\n\n        return isQualified;\n    }\n    return result.booleanValue();\n}",
                "start_point": {
                    "row": 63,
                    "column": 4
                },
                "end_point": {
                    "row": 77,
                    "column": 5
                }
            }
        ],
        "class_mode": "Modified"
    }
]